{"cameraMode":{"drawMode":0,"name":"Shaded","section":"Shading Mode"},"sceneLighting":true,"audioPlay":false,"sceneViewState":{"m_AlwaysRefresh":false,"showFog":true,"showSkybox":true,"showFlares":true,"showImageEffects":true,"showParticleSystems":true,"showVisualEffectGraphs":true,"m_FxEnabled":true},"in2DMode":false,"pivot":{"x":0.9439610242843628,"y":0.6670143604278565,"z":-1.2008558511734009},"rotation":{"x":-0.020613526925444604,"y":0.9789998531341553,"z":-0.12879808247089387,"w":-0.15668383240699769},"size":2.3682355880737306,"orthographic":false}